LICENSE
MANIFEST.in
README.md
requirements.txt
setup.py
cp2stdout/__init__.py
cp2stdout/__main__.py
cp2stdout/config.py
cp2stdout.egg-info/PKG-INFO
cp2stdout.egg-info/SOURCES.txt
cp2stdout.egg-info/dependency_links.txt
cp2stdout.egg-info/entry_points.txt
cp2stdout.egg-info/requires.txt
cp2stdout.egg-info/top_level.txt