Metadata-Version: 2.1
Name: cp2stdout
Version: 1.1.1
Summary: COOPER to stdout
Home-page: https://github.com/hardwario/cp2stdout
Author: HARDWARIO s.r.o.
Author-email: ask@hardwario.com
License: MIT
Keywords: cooper,zmq,iot,stdout
Platform: any
Classifier: Development Status :: 5 - Production/Stable
Classifier: Environment :: Console
Classifier: Intended Audience :: Developers
Classifier: License :: OSI Approved :: MIT License
Classifier: Natural Language :: English
Classifier: Operating System :: OS Independent
Classifier: Programming Language :: Python :: 3
Classifier: Topic :: Utilities
